django_frontera/__init__.py
django_frontera/configuration/__init__.py
django_frontera/configuration/apps.py
django_frontera/configuration/models.py
django_frontera/configuration/management/commands/showurls.py
django_frontera/configuration/migrations/0001_initial.py
django_frontera/configuration/migrations/0002_auto_20191017_1646.py
django_frontera/configuration/migrations/0003_auto_20191017_1941.py
django_frontera/configuration/migrations/__init__.py
django_frontera/contrib/__init__.py
django_frontera/contrib/aws/S3.py
django_frontera/contrib/aws/__init__.py
django_frontera/contrib/aws/extras/S3-bucket-CORS.xml
django_frontera/contrib/aws/extras/S3-bucket-policy.json
django_frontera/contrib/benchmarking/__init__.py
django_frontera/contrib/benchmarking/querying.py
django_frontera/contrib/benchmarking/timer.py
django_frontera/contrib/django/__init__.py
django_frontera/contrib/django/authentication.py
django_frontera/contrib/django/authenticationForms.py
django_frontera/contrib/django/loggers.py
django_frontera/contrib/django/login_backends.py
django_frontera/contrib/django/messages.py
django_frontera/contrib/django/models.py
django_frontera/contrib/jinja2/__init__.py
django_frontera/contrib/jinja2/environment.py
django_frontera/contrib/templates/400.html
django_frontera/contrib/templates/403.html
django_frontera/contrib/templates/404.html
django_frontera/contrib/templates/500.html
django_frontera/contrib/templates/macros/ahrefs.jinja2
django_frontera/contrib/templates/macros/crazyegg.jinja2
django_frontera/contrib/templates/macros/facebook_pixel.jinja2
django_frontera/contrib/templates/macros/google_analytics.jinja2
django_frontera/contrib/templates/macros/google_plus.jinja2
django_frontera/contrib/templates/macros/google_site_verification.jinja2
django_frontera/contrib/templates/macros/google_tagmanager.jinja2
django_frontera/contrib/templates/macros/opengraph.jinja2
django_frontera-0.0.2.dist-info/DESCRIPTION.rst
django_frontera-0.0.2.dist-info/METADATA
django_frontera-0.0.2.dist-info/RECORD
django_frontera-0.0.2.dist-info/WHEEL
django_frontera-0.0.2.dist-info/metadata.json
django_frontera-0.0.2.dist-info/top_level.txt
