Metadata-Version: 2.0
Name: django-frontera
Version: 0.0.2
Summary: Utils used by Frontera.
Home-page: https://nuu.co/
Author: frontera-hq
Author-email: daniel.ortiz@nuu.co
License: MIT
Platform: UNKNOWN
Classifier: Development Status :: 3 - Alpha
Classifier: Environment :: Web Environment
Classifier: Intended Audience :: Developers
Classifier: Operating System :: OS Independent
Classifier: License :: OSI Approved :: MIT License
Classifier: Programming Language :: Python
Classifier: Programming Language :: Python :: 3
Classifier: Programming Language :: Python :: 3.5
Classifier: Programming Language :: Python :: 3.6
Classifier: Programming Language :: Python :: 3.7
Classifier: Programming Language :: Python :: 3.8
Classifier: Framework :: Django
Classifier: Framework :: Django :: 2.1
Classifier: Framework :: Django :: 2.2
Classifier: Framework :: Wagtail
Classifier: Topic :: Utilities
Provides-Extra: testing
Provides-Extra: docs
Provides-Extra: docs
Provides-Extra: testing
Requires-Dist: jinjalint (>=0.5); extra == 'testing'
